gpac/_BandPassFilter.py
gpac/_BaseFilter1D.py
gpac/_DifferenciableBandPassFilter.py
gpac/_Hilbert.py
gpac/_ModulationIndex.py
gpac/_PAC.py
gpac/_SyntheticDataGenerator.py
gpac/_SyntheticDataGenerator_v01.py
gpac/__init__.py
gpac/_calculate_pac.py
gpac/_decorators.py
gpac/_pac.py
gpac/_utils.py
gpac/playground.py
torch_pac-0.1.0.dist-info/licenses/LICENSE
torch_pac-0.1.0.dist-info/METADATA
torch_pac-0.1.0.dist-info/WHEEL
torch_pac-0.1.0.dist-info/top_level.txt
torch_pac-0.1.0.dist-info/RECORD
