Metadata-Version: 2.4
Name: torch-pac
Version: 0.1.0
Summary: GPU-Accelerated Phase-Amplitude Coupling calculation using PyTorch
Author-email: Yusuke Watanabe <ywatanabe@alumni.u-tokyo.ac.jp>
License: Copyright 2025 Yusuke Watanabe (ywatanabe@alumni.u-tokyo.ac.jp)
Project-URL: Homepage, https://github.com/ywatanabe1989/gPAC
Project-URL: Repository, https://github.com/ywatanabe1989/gPAC
Project-URL: Bug Tracker, https://github.com/ywatanabe1989/gPAC/issues
Classifier: Programming Language :: Python :: 3
Classifier: License :: OSI Approved :: MIT License
Classifier: Operating System :: OS Independent
Classifier: Intended Audience :: Science/Research
Classifier: Topic :: Scientific/Engineering
Classifier: Topic :: Software Development :: Libraries :: Python Modules
Requires-Python: >=3.8
License-File: LICENSE
Requires-Dist: torch>=1.9.0
Requires-Dist: numpy
Requires-Dist: scipy
Requires-Dist: torchaudio>=0.9.0
Dynamic: license-file
